LICENSE
MANIFEST.in
README
requirements.txt
setup.py
doc_src/Makefile
doc_src/conf.py
doc_src/getting_started.rst
doc_src/index.rst
doc_src/installation.rst
doc_src/make.bat
doc_src/_static/breadcrumb_background.png
doc_src/_static/default.css
doc_src/_static/documentation.png
doc_src/_static/header_sm_mid.png
doc_src/_static/scrn1.png
doc_src/_static/scrn2.png
doc_src/_static/searchfield_leftcap.png
doc_src/_static/searchfield_repeat.png
doc_src/_static/searchfield_rightcap.png
doc_src/_static/title_background.png
doc_src/_static/toc.js
doc_src/_static/triangle_closed.png
doc_src/_static/triangle_left.png
doc_src/_static/triangle_open.png
doc_src/_templates/layout.html
doc_src/reference/index.rst
doc_src/reference/settings.rst
pollit/__init__.py
pollit/admin.py
pollit/forms.py
pollit/models.py
pollit/settings.py
pollit/tests.py
pollit/urls.py
pollit/views.py
pollit.egg-info/PKG-INFO
pollit.egg-info/SOURCES.txt
pollit.egg-info/dependency_links.txt
pollit.egg-info/top_level.txt
pollit/migrations/0001_initial.py
pollit/migrations/0002_auto__add_field_pollchoicedata_ip__chg_field_pollchoicedata_user.py
pollit/migrations/__init__.py
pollit/templates/pollit/comments.html
pollit/templates/pollit/detail.html
pollit/templates/pollit/index.html
pollit/templates/pollit/results.html