Metadata-Version: 1.0
Name: pollit
Version: 0.2.5
Summary: An application for creating polls and tabulating results
Home-page: http://opensource.washingtontimes.com/projects/pollit/
Author: Jose Soares
Author-email: jsoares@washingtontimes.com
License: UNKNOWN
Platform: UNKNOWN
Classifier: Framework :: Django
Classifier: License :: OSI Approved :: Apache Software License
Classifier: Development Status :: 4 - Beta
Classifier: Environment :: Other Environment
Classifier: Programming Language :: Python
